showdown/__init__.py
showdown/showdown.py
showdown.ssh-0.1.0.dist-info/LICENSE
showdown.ssh-0.1.0.dist-info/METADATA
showdown.ssh-0.1.0.dist-info/WHEEL
showdown.ssh-0.1.0.dist-info/top_level.txt
showdown.ssh-0.1.0.dist-info/RECORD
