Metadata-Version: 2.1
Name: showdown.ssh
Version: 0.1.0
Summary: A tool to automate local network health checks
Home-page: https://github.com/boshimoto/showdown
Author: Boshimoto
Author-email: author@example.com
License: MIT License
Project-URL: Bug Tracker, https://github.com/boshimoto/showdown/issues
Platform: UNKNOWN
Classifier: Programming Language :: Python :: 3
Classifier: License :: OSI Approved :: MIT License
Classifier: Operating System :: OS Independent
Requires-Python: >=3.8
License-File: LICENSE
Requires-Dist: netmiko (>=3.4.0)
Requires-Dist: setuptools (>=60.5.0)
Requires-Dist: paramiko (>=2.7.2)
Requires-Dist: scp (>=0.13.6)
Requires-Dist: tenacity
Requires-Dist: textfsm (>=1.1.2)
Requires-Dist: ntc-templates (>=2.1.0)
Requires-Dist: pyserial
Requires-Dist: importlib-resources ; python_version < "3.8"
